gpkg.slim-0.5.1-py2.7-nspkg.pth
gpkg/slim/__init__.py
gpkg/slim/_custom_dataset.py
gpkg/slim/_tfrecord.py
gpkg/slim/_util.py
gpkg/slim/eval.py
gpkg/slim/export_and_freeze.py
gpkg/slim/guild.yml
gpkg/slim/images_prepare.py
gpkg/slim/train.py
gpkg.slim-0.5.1.dist-info/METADATA
gpkg.slim-0.5.1.dist-info/PACKAGE
gpkg.slim-0.5.1.dist-info/RECORD
gpkg.slim-0.5.1.dist-info/WHEEL
gpkg.slim-0.5.1.dist-info/namespace_packages.txt
gpkg.slim-0.5.1.dist-info/top_level.txt
